README.md
setup.cfg
setup.py
battlerite_client/__init__.py
battlerite_client/client.py
battlerite_client/constants.py
battlerite_client/helpers.py
battlerite_client/match.py
battlerite_client/participant.py
battlerite_client/player.py
battlerite_client/response.py
battlerite_client/roster.py
battlerite_client/round.py
battlerite_client/team.py
battlerite_client.egg-info/PKG-INFO
battlerite_client.egg-info/SOURCES.txt
battlerite_client.egg-info/dependency_links.txt
battlerite_client.egg-info/not-zip-safe
battlerite_client.egg-info/requires.txt
battlerite_client.egg-info/top_level.txt