Metadata-Version: 1.0
Name: battlerite-client
Version: 0.1
Summary: Battlerite REST API client
Home-page: https://github.com/DrPandemic/battlerite-client
Author: DrPandemic
Author-email: UNKNOWN
License: MIT
Platform: UNKNOWN
